{
  "01": "01",
  "02": "02",
  "03": "03",
  "04": "04",
  "A base for future verified project assets": "Основа для будущих проверенных проектных материалов",
  "A clean placeholder for later verified case media": "Чистый заполнитель для последующих проверенных медиаматериалов кейсов",
  "A future-ready page system for verified project additions": "Готовая к будущему система страниц для добавления проверенных проектов",
  "A reusable site-level reference structure": "Многоразовая эталонная структура на уровне сайта",
  "A reusable structure for similar small data center needs": "Многоразовая структура для схожих потребностей небольших центров обработки данных",
  "A structured explanation for recurring storage opportunities": "Структурированное объяснение повторяющихся возможностей в области накопления энергии",
  "About Powerlink Energy": "О Powerlink Energy",
  "About Us": "О нас",
  "Accessory and monitoring support items": "Аксессуары и компоненты поддержки мониторинга",
  "Adapts well to distributed deployment conditions.": "Хорошо адаптируется к условиям распределённого развёртывания.",
  "Application": "Применение",
  "Application first": "Сначала применение",
  "Application first, assets second": "Сначала применение, затем материалы",
  "Applications": "Применения",
  "Applications We Serve": "Области применения, которые мы обслуживаем",
  "Back to {label}": "Назад к {label}",
  "Backup power configuration reference for compact server rooms and IDC environments.": "Эталонная конфигурация резервного питания для компактных серверных и сред IDC.",
  "Backup power integration reference environment": "Эталонная среда интеграции резервного питания",
  "Backup power systems for IT, telecom, edge, and industrial applications that require stable power continuity.": "Системы резервного питания для IT, телеком, edge и промышленных приложений, требующих стабильной непрерывности питания.",
  "Balance runtime, battery footprint, and project budget.": "Баланс между временем автономной работы, габаритами АКБ и бюджетом проекта.",
  "Base stations and telecom rooms": "Базовые станции и телекоммуникационные помещения",
  "Basic accessories and monitoring for safe operation.": "Базовые аксессуары и мониторинг для безопасной эксплуатации.",
  "Battery bank": "Аккумуляторный блок",
  "Battery bank matched to site autonomy requirements.": "Аккумуляторный блок, соответствующий требованиям автономности объекта.",
  "Battery bank or rack modules": "Аккумуляторный блок или стоечные модули",
  "Battery expansion and accessory options": "Варианты расширения АКБ и аксессуаров",
  "Battery management related components": "Компоненты, связанные с управлением АКБ",
  "Battery pack sized for short to medium runtime support.": "Аккумуляторный модуль, рассчитанный на краткую и среднюю автономную работу.",
  "Battery storage rack or cabinet.": "Стойка или шкаф для хранения АКБ.",
  "Battery storage unit": "Блок накопления энергии на АКБ",
  "Benefits": "Преимущества",
  "Better alignment between customer need and product scope": "Лучшее соответствие между потребностями клиента и ассортиментом продукции",
  "Built Around Workable Power Solutions": "Построено вокруг практичных решений по электропитанию",
  "Built for customers who need practical project support instead of a generic product list.": "Создано для клиентов, которым нужна практическая проектная поддержка, а не общий список продукции.",
  "Cabinet-level storage options": "Варианты накопления на уровне шкафа",
  "Category Overview": "Обзор категории",
  "Category Scope": "Область категории",
  "Category supply": "Поставка по категориям",
  "Clear communication": "Чёткая коммуникация",
  "Clearer project communication at quotation stage": "Более ясная проектная коммуникация на этапе коммерческого предложения",
  "Combine the right product categories into a practical solution path.": "Объедините нужные категории продукции в практичный путь решения.",
  "Combines core DC equipment with supporting accessories.": "Объединяет основное DC-оборудование с вспомогательными аксессуарами.",
  "Commercial & Industrial Energy Storage": "Коммерческое и промышленное накопление энергии",
  "Commercial and industrial energy storage equipment": "Оборудование для коммерческого и промышленного накопления энергии",
  "Commercial energy storage and integrated power equipment": "Коммерческое накопление энергии и интегрированное силовое оборудование",
  "Communication:": "Связь:",
  "Compact UPS host or distributed backup module.": "Компактный UPS-хост или распределённый резервный модуль.",
  "Compact and efficient power systems for edge nodes, distributed IT loads, and space-limited installations.": "Компактные и эффективные системы питания для edge-узлов, распределённых IT-нагрузок и установок с ограниченным пространством.",
  "Compact power equipment for distributed IT loads": "Компактное силовое оборудование для распределённых IT-нагрузок",
  "Compact server rooms and IDC environments": "Компактные серверные и среды IDC",
  "Company": "Компания",
  "Completes the accessory layer of power projects.": "Дополняет аксессуарный уровень силовых проектов.",
  "Configuration": "Конфигурация",
  "Contact": "Контакты",
  "Contact Powerlink Energy for UPS, battery, inverter, telecom power, and integrated solution inquiries.": "Свяжитесь с Powerlink Energy по вопросам UPS, АКБ, инверторов, телеком-питания и интегрированных решений.",
  "Contact Us": "Связаться с нами",
  "Contact Us | Powerlink Energy": "Связаться с нами | Powerlink Energy",
  "Cooperation style:": "Формат сотрудничества:",
  "Coordinate quotation, sourcing, and delivery communication clearly.": "Чётко координируйте коммуникацию по коммерческому предложению, закупке и поставке.",
  "Core Equipment Categories": "Основные категории оборудования",
  "Country": "Страна",
  "Customer Challenges": "Задачи клиентов",
  "Customers need a configuration path that is clear before deeper engineering.": "Клиентам нужен понятный путь конфигурации до углублённого проектирования.",
  "Customers usually need a practical structure showing how UPS, batteries, and supporting distribution can work together before deeper engineering review.": "Клиентам обычно нужна практичная структура, показывающая, как UPS, АКБ и вспомогательное распределение работают вместе, до углублённой инженерной проверки.",
  "Customers want a practical list that goes beyond a single product SKU.": "Клиенты хотят практичный перечень, выходящий за рамки одного SKU.",
  "DC modules and support hardware": "DC-модули и вспомогательное оборудование",
  "DC/DC modules": "DC/DC модули",
  "Data Center Backup Power": "Резервное питание для центров обработки данных",
  "Data Centers": "Центры обработки данных",
  "Data center and backup power equipment environment": "Среда оборудования для ЦОД и резервного питания",
  "Delivery Support": "Поддержка поставки",
  "Different homes require different balances between backup, self-consumption, and budget.": "Разным домохозяйствам нужен разный баланс между резервом, автопотреблением и бюджетом.",
  "Different monitoring environments require different combinations of probes, cabling, and integration items.": "Разные среды мониторинга требуют разных комбинаций датчиков, кабелей и интеграционных компонентов.",
  "Direct Communication": "Прямая коммуникация",
  "Direct Contact": "Прямой контакт",
  "Distributed storage equipment reference": "Эталон распределённого накопительного оборудования",
  "Distributed telecom projects often need a clearer explanation of runtime planning, rectifier or UPS selection, and field accessory scope.": "Распределённые телеком-проекты часто требуют более ясного объяснения планирования автономной работы, выбора выпрямителя или UPS и объёма полевых аксессуаров.",
  "Distribution and monitoring accessories": "Аксессуары распределения и мониторинга",
  "Each page explains the typical need, design logic, recommended configuration, and future project media in one reusable template.": "Каждая страница объясняет типовую потребность, логику проектирования, рекомендуемую конфигурацию и будущие проектные материалы в одном многоразовом шаблоне.",
  "Edge Computing": "Edge computing",
  "Edge Computing Power": "Питание для edge computing",
  "Edge sites often have limited rack or cabinet space.": "На edge-объектах часто ограничено пространство для стоек или шкафов.",
  "Email": "Электронная почта",
  "Email Us": "Напишите нам",
  "Energy storage package reference for peak shaving, backup power, and site-level energy management.": "Эталонный пакет накопления энергии для сглаживания пиков, резервного питания и управления энергией на уровне объекта.",
  "Energy storage support projects": "Проекты поддержки накопления энергии",
  "Energy-linked conversion projects": "Проекты преобразования, связанные с энергией",
  "Environmental and deployment differences increase configuration complexity.": "Различия в среде и развёртывании увеличивают сложность конфигурации.",
  "Environmental and safety monitoring": "Экологический и безопасностный мониторинг",
  "Expandable": "Масштабируемый",
  "Explore Powerlink Energy product categories for UPS, batteries, inverters, telecom power, and monitoring accessories.": "Изучите категории продукции Powerlink Energy: UPS, АКБ, инверторы, телеком-питание и аксессуары мониторинга.",
  "Explore Powerlink Energy reference frameworks for recurring application structures and future project libraries.": "Изучите эталонные фреймворки Powerlink Energy для повторяющихся структур применения и будущих проектных библиотек.",
  "Explore Solutions": "Изучить решения",
  "Explore scenario-based integrated power solutions from Powerlink Energy.": "Изучите интегрированные силовые решения Powerlink Energy, основанные на сценариях.",
  "Explore solution": "Изучить решение",
  "Fast Response": "Быстрый отклик",
  "Fast Response, Practical Matching, One Supply Path": "Быстрый отклик, практичный подбор, единый канал поставки",
  "Fast Solution Matching": "Быстрый подбор решения",
  "Fast follow-up": "Быстрое сопровождение",
  "Fast project response": "Быстрый ответ по проекту",
  "Field integration accessories reference": "Эталон аксессуаров полевой интеграции",
  "Fit backup equipment into limited technical room space.": "Разместить резервное оборудование в ограниченном техническом помещении.",
  "Fits both residential and light commercial discussions.": "Подходит для обсуждений в жилом и лёгком коммерческом сегментах.",
  "Fits multiple deployment scales.": "Подходит для разных масштабов развёртывания.",
  "Fits projects that need practical, entry-friendly configuration.": "Подходит для проектов, требующих практичной и доступной конфигурации.",
  "Flexible Cooperation": "Гибкое сотрудничество",
  "Flexible MOQ": "Гибкий MOQ",
  "Framework Overview": "Обзор фреймворка",
  "Get a Quote": "Получить коммерческое предложение",
  "Helps combine conversion and storage planning.": "Помогает объединить планирование преобразования и накопления.",
  "Helps combine inverter and storage selection into one path.": "Помогает объединить выбор инвертора и накопления в один путь.",
  "Helps structure product matching around real site goals.": "Помогает структурировать подбор продукции вокруг реальных целей объекта.",
  "Home": "Главная",
  "How We Structure Frameworks": "Как мы структурируем фреймворки",
  "How We Work": "Как мы работаем",
  "Hybrid / Solar Inverters": "Гибридные / солнечные инверторы",
  "Hybrid and solar inverter categories for residential, commercial, and storage-linked power conversion applications.": "Категории гибридных и солнечных инверторов для жилых, коммерческих и связанных с накоплением приложений преобразования энергии.",
  "Hybrid inverter and battery storage setup": "Конфигурация гибридного инвертора и накопления на АКБ",
  "Hybrid inverter and solar storage equipment": "Оборудование гибридного инвертора и солнечного накопления",
  "Hybrid inverter or solar inverter.": "Гибридный инвертор или солнечный инвертор.",
  "Hybrid inverter reference equipment": "Эталонное оборудование гибридного инвертора",
  "Hybrid inverter units": "Блоки гибридного инвертора",
  "Hybrid or PCS inverter": "Гибридный инвертор или PCS",
  "Hybrid or PCS inverter matched to the application profile.": "Гибридный инвертор или PCS, соответствующий профилю применения.",
  "Hybrid solar and battery solutions for homes and small offices requiring stable power and backup capability.": "Гибридные солнечные и аккумуляторные решения для домов и небольших офисов, требующих стабильного питания и резервных возможностей.",
  "If you are looking for a practical power solution instead of a generic product list, Powerlink Energy is ready to support your project.": "Если вам нужно практичное решение по электропитанию, а не общий список продукции, Powerlink Energy готов поддержать ваш проект.",
  "Improved clarity for telecom project discussions": "Повышенная ясность обсуждений телеком-проектов",
  "Improves category completeness for safety-oriented sourcing.": "Повышает полноту категорий для закупок, ориентированных на безопасность.",
  "Improves energy density for many projects.": "Повышает плотность энергии для многих проектов.",
  "Improves power continuity for critical IT equipment.": "Повышает непрерывность питания для критичного IT-оборудования.",
  "Improves project readiness with integration parts included.": "Повышает готовность проекта за счёт включения интеграционных компонентов.",
  "Industrial DC support scenarios": "Сценарии промышленной DC-поддержки",
  "Industrial M12 cabling": "Промышленная кабельная система M12",
  "Industrial cabling and connection parts for deployment.": "Промышленная кабельная система и соединительные детали для развёртывания.",
  "Industrial control and edge environments": "Среды промышленного управления и edge",
  "Industrial integration projects": "Промышленные интеграционные проекты",
  "Input and output distribution accessories with monitoring support.": "Аксессуары распределения входа/выхода с поддержкой мониторинга.",
  "Inquiry Form": "Форма запроса",
  "Installers need a clear hardware scope for quotation and planning.": "Монтажникам нужен чёткий объём оборудования для коммерческого предложения и планирования.",
  "Instead of offering only standalone products, we help customers combine the right equipment into workable power solution packages.": "Вместо того чтобы предлагать только отдельные продукты, мы помогаем клиентам объединять нужное оборудование в работоспособные пакеты силовых решений.",
  "Instead of only offering standalone products, we emphasize application-based matching and one-stop integration.": "Вместо того чтобы предлагать только отдельные продукты, мы делаем акцент на подборе по применению и интеграции «под ключ».",
  "Integrated Categories for Critical Applications": "Интегрированные категории для критичных приложений",
  "Integrated Power Solutions for Critical Applications": "Интегрированные силовые решения для критичных приложений",
  "Integrated Supply": "Интегрированная поставка",
  "Integrated backup power for telecom towers and remote communication sites with stable performance and flexible configuration.": "Интегрированное резервное питание для телеком-вышек и удалённых коммуникационных объектов со стабильными характеристиками и гибкой конфигурацией.",
  "Integrated backup solution reference for telecom towers and distributed sites.": "Эталон интегрированного резервного решения для телеком-вышек и распределённых объектов.",
  "Integrated power and energy storage equipment": "Интегрированное силовое и накопительное оборудование",
  "Integrated support": "Интегрированная поддержка",
  "Integrated telecom and backup power equipment for project inquiries": "Интегрированное телеком- и резервное оборудование для проектных запросов",
  "Integration-ready": "Готов к интеграции",
  "JavaScript is optional on this site. Core navigation and page content remain available without it.": "JavaScript на этом сайте необязателен. Основная навигация и содержимое страниц доступны и без него.",
  "Keeps configuration aligned with target runtime and site conditions.": "Сохраняет конфигурацию согласованной с целевой автономной работой и условиями объекта.",
  "Keeps equipment footprint aligned with compact environments.": "Сохраняет габариты оборудования согласованными с компактными средами.",
  "Key Benefits": "Ключевые преимущества",
  "Learn how Powerlink Energy approaches integrated power supply for critical applications.": "Узнайте, как Powerlink Energy подходит к интегрированному электропитанию для критичных приложений.",
  "Learn more": "Подробнее",
  "Links sensing accessories with the surrounding power context.": "Связывает сенсорные аксессуары с окружающим контекстом питания.",
  "Lithium Battery Systems": "Литиевые аккумуляторные системы",
  "Lithium battery pack matched to backup and energy goals.": "Литиевый аккумуляторный модуль, соответствующий целям резерва и энергопотребления.",
  "Lithium battery storage": "Литиевое накопление энергии",
  "Lithium battery storage system equipment": "Оборудование литиевой системы накопления энергии",
  "Lithium battery storage systems for backup power, telecom, and energy storage projects requiring practical integration.": "Литиевые системы накопления для резервного питания, телекома и проектов накопления энергии, требующих практичной интеграции.",
  "Lithium battery systems support backup, storage, and telecom applications that need practical runtime planning and flexible system matching.": "Литиевые системы поддерживают резерв, накопление и телеком-приложения, требующие практичного планирования автономной работы и гибкого подбора системы.",
  "Lithium or VRLA battery bank for the required backup duration.": "Литиевый или VRLA аккумуляторный блок для требуемой длительности резерва.",
  "Looking for UPS systems, battery storage, telecom power equipment, industrial cabling, or a customized power solution package? Send us your project details and we will get back to you as soon as possible.": "Ищете UPS, накопление на АКБ, телеком-питание, промышленную кабельную систему или индивидуальный пакет силового решения? Отправьте детали проекта — мы ответим как можно скорее.",
  "M12 and industrial connection cabling": "Кабельная система M12 и промышленные соединения",
  "Main Configuration": "Основная конфигурация",
  "Maintain stable output during utility instability or outages.": "Поддерживать стабильный выход при нестабильности или отключении сети.",
  "Makes later engineering handoff easier with a clearer product scope.": "Облегчает последующую передачу в инженерию за счёт более чёткого объёма продукции.",
  "Match": "Подбор",
  "Menu": "Меню",
  "Message": "Сообщение",
  "Monitoring & Industrial Cabling": "Мониторинг и промышленная кабельная система",
  "Monitoring accessories and field parts": "Аксессуары мониторинга и полевые компоненты",
  "Monitoring accessories and industrial integration equipment": "Аксессуары мониторинга и оборудование промышленной интеграции",
  "Monitoring accessories, sensing components, and industrial cabling for power integration and supervision applications.": "Аксессуары мониторинга, сенсорные компоненты и промышленная кабельная система для интеграции питания и приложений надзора.",
  "Monitoring and connection accessories for fast deployment.": "Аксессуары мониторинга и соединения для быстрого развёртывания.",
  "Monitoring and protection accessories": "Аксессуары мониторинга и защиты",
  "Monitoring and sensing accessories": "Аксессуары мониторинга и датчиков",
  "Monitoring host or power support equipment.": "Хост мониторинга или оборудование поддержки питания.",
  "Monitoring modules, breakers, and cabling for field integration.": "Модули мониторинга, автоматические выключатели и кабельная система для полевой интеграции.",
  "Monitoring, distribution, and safety accessories for site integration.": "Аксессуары мониторинга, распределения и безопасности для интеграции на объекте.",
  "Monitoring, protection, and distribution accessories": "Аксессуары мониторинга, защиты и распределения",
  "Monitoring-oriented solution packages for temperature sensing, environmental supervision, and safety-related applications.": "Пакеты решений, ориентированные на мониторинг, для температурного контроля, экологического надзора и приложений, связанных с безопасностью.",
  "Name": "Имя",
  "Need practical product matching for your application?": "Нужен практичный подбор продукции для вашего применения?",
  "Next Step": "Следующий шаг",
  "One-Stop Integration": "Интеграция «под ключ»",
  "Online UPS host": "Online UPS хост",
  "Online UPS host sized to the target IT load.": "Online UPS хост, рассчитанный на целевую IT-нагрузку.",
  "Online UPS units": "Блоки online UPS",
  "Our product portfolio supports both standard supply and integrated project configurations for buyers who already know their technical category.": "Наш портфель продукции поддерживает как стандартные поставки, так и интегрированные проектные конфигурации для покупателей, уже знающих свою техническую категорию.",
  "Our product portfolio supports both standard supply and integrated project configurations.": "Наш портфель продукции поддерживает стандартные поставки и интегрированные проектные конфигурации.",
  "Our reference frameworks explain typical application structures now and can evolve into a verified project library later.": "Наши эталонные фреймворки уже объясняют типовые структуры применения и позже могут развиться в проверенную проектную библиотеку.",
  "Overview": "Обзор",
  "Pain Points": "Болевые точки",
  "Peak shaving, backup power, and site-level energy management": "Сглаживание пиков, резервное питание и управление энергией на уровне объекта",
  "Power accessory completion": "Дополнение силовых аксессуаров",
  "Power monitoring and industrial supervision equipment": "Оборудование мониторинга питания и промышленного надзора",
  "Power support still needs continuity despite small deployment scale.": "Поддержка питания должна оставаться непрерывной даже при небольшом масштабе развёртывания.",
  "Powerlink Energy": "Powerlink Energy",
  "Powerlink Energy integrated power solutions for critical applications": "Интегрированные силовые решения Powerlink Energy для критичных приложений",
  "Powerlink Energy is a solution-driven supplier specializing in integrated power systems for critical applications.": "Powerlink Energy — поставщик, ориентированный на решения, специализирующийся на интегрированных силовых системах для критичных приложений.",
  "Powerlink Energy provides UPS systems, energy storage solutions, telecom power equipment, DC/DC modules, industrial cabling, and monitoring accessories for data centers, telecom sites, commercial energy storage, and other demanding environments.": "Powerlink Energy поставляет UPS, решения для накопления энергии, телеком-питание, DC/DC модули, промышленную кабельную систему и аксессуары мониторинга для центров обработки данных, телеком-объектов, коммерческого накопления энергии и других требовательных сред.",
  "Powerlink Energy | Integrated Power Solutions": "Powerlink Energy | Интегрированные силовые решения",
  "Practical Collaboration Process": "Практичный процесс сотрудничества",
  "Practical Support for Mission-Critical Environments": "Практичная поддержка для критически важных сред",
  "Practical delivery path": "Практичный путь поставки",
  "Practical storage solutions for peak shaving, backup power, and energy management in commercial and industrial environments.": "Практичные решения накопления для сглаживания пиков, резервного питания и управления энергией в коммерческих и промышленных средах.",
  "Primary navigation": "Основная навигация",
  "Product": "Продукт",
  "Product Categories": "Категории продукции",
  "Product Categories for Direct Category Buyers": "Категории продукции для покупателей с чёткой категорией",
  "Product Category": "Категория продукции",
  "Product Interest": "Интересующая продукция",
  "Products": "Продукция",
  "Products | Powerlink Energy": "Продукция | Powerlink Energy",
  "Professional Positioning": "Профессиональное позиционирование",
  "Professional and Dependable": "Профессионально и надёжно",
  "Project support": "Проектная поддержка",
  "Project visuals will be added later": "Визуальные материалы проекта будут добавлены позже",
  "Project-ready": "Готов к проекту",
  "Projects benefit from compact, integration-ready hardware combinations.": "Проекты выигрывают от компактных, готовых к интеграции аппаратных комбинаций.",
  "Projects need a workable combination of storage, inverter, and protection devices.": "Проектам нужна работоспособная комбинация накопления, инвертора и защитных устройств.",
  "Projects often need both power support and sensing accessories.": "Проектам часто нужны и поддержка питания, и сенсорные аксессуары.",
  "Projects often require practical combinations of rectifiers, batteries, and accessories.": "Проекты часто требуют практичных комбинаций выпрямителей, АКБ и аксессуаров.",
  "Protection, monitoring, and connection accessories": "Аксессуары защиты, мониторинга и соединения",
  "Provides a practical supply path for telecom power projects.": "Обеспечивает практичный канал поставки для телеком-проектов по питанию.",
  "Rack and tower form factors": "Форм-факторы rack и tower",
  "Rack battery modules": "Стоечные аккумуляторные модули",
  "Reach Our Team Directly": "Связаться с нашей командой напрямую",
  "Recommended Configuration": "Рекомендуемая конфигурация",
  "Rectifier systems": "Системы выпрямителей",
  "Reference Design": "Эталонное проектирование",
  "Reference Framework": "Эталонный фреймворк",
  "Reference Frameworks": "Эталонные фреймворки",
  "Reference Frameworks That Can Grow Into a Real Case Library": "Эталонные фреймворки, которые могут вырасти в реальную библиотеку кейсов",
  "Reference Frameworks for Future Project Expansion": "Эталонные фреймворки для будущего расширения проектов",
  "Reference Frameworks | Powerlink Energy": "Эталонные фреймворки | Powerlink Energy",
  "Reference Outcome": "Эталонный результат",
  "Reference Structures That Can Scale": "Масштабируемые эталонные структуры",
  "Reference Visuals": "Эталонные визуалы",
  "Reference visual for commercial and industrial energy storage": "Эталонный визуал для коммерческого и промышленного накопления энергии",
  "Reference visual for compact data center backup power": "Эталонный визуал для резервного питания компактного ЦОД",
  "Reference visual for telecom base station backup power": "Эталонный визуал для резервного питания телеком базовой станции",
  "Reference visuals illustrate typical equipment scope. Verified customer project photos will replace these when approved.": "Эталонные визуалы иллюстрируют типовой объём оборудования. После одобрения их заменят проверенные фото клиентских проектов.",
  "Reliable backup power solutions for small and medium-sized server rooms, IDC facilities, and network cabinets.": "Надёжные решения резервного питания для серверных малого и среднего размера, объектов IDC и сетевых шкафов.",
  "Remote communication deployments": "Развёртывания удалённой связи",
  "Remote sites need high reliability with limited on-site service.": "Удалённые объекты требуют высокой надёжности при ограниченном обслуживании на месте.",
  "Residential Solar Storage": "Жилое солнечное накопление",
  "Residential solar storage": "Жилое солнечное накопление",
  "Responsive Support": "Оперативная поддержка",
  "Review the application, power requirement, and market context.": "Изучите применение, требования к мощности и рыночный контекст.",
  "Safety Monitoring Applications": "Приложения мониторинга безопасности",
  "Safety Monitoring Solutions": "Решения мониторинга безопасности",
  "Scenario coverage:": "Охват сценариев:",
  "Scenario-Based Power Solutions": "Силовые решения на основе сценариев",
  "Scenario-Based Solutions": "Решения на основе сценариев",
  "Scenario-Based Thinking": "Сценарное мышление",
  "Scenario-driven content": "Контент, ориентированный на сценарии",
  "Scenario-driven power solutions for data centers, telecom sites, energy storage, and other critical applications.": "Силовые решения на основе сценариев для центров обработки данных, телеком-объектов, накопления энергии и других критичных приложений.",
  "Scenario-first supply support for power-sensitive and mission-critical applications.": "Поддержка поставок «сценарий в первую очередь» для приложений, чувствительных к питанию и критически важных.",
  "Scenario-first, integration-focused": "Сначала сценарий, фокус на интеграции",
  "Scenario-led": "Сценарно-ориентированный",
  "Scope": "Объём",
  "Send Your Application Brief and We Will Match the Right Direction": "Отправьте описание применения — мы подберём правильное направление",
  "Send Your Inquiry": "Отправить запрос",
  "Sensors and probes": "Датчики и зонды",
  "Sensors, probes, or field accessories matched to the environment.": "Датчики, зонды или полевые аксессуары, соответствующие среде.",
  "Server rooms and data cabinets": "Серверные и шкафы данных",
  "Share your application, target market, and requirement range. We will help you match the right direction quickly.": "Расскажите о применении, целевом рынке и диапазоне требований. Мы быстро поможем определить правильное направление.",
  "Simplifies sourcing for small but power-sensitive deployments.": "Упрощает закупку для небольших, но чувствительных к питанию развёртываний.",
  "Simplifies sourcing with matched core equipment and accessories.": "Упрощает закупку за счёт согласованного основного оборудования и аксессуаров.",
  "Site objectives vary between backup, arbitrage, and energy optimization.": "Цели объекта варьируются между резервом, арбитражем и оптимизацией энергии.",
  "Small Data Center Backup Power": "Резервное питание для небольшого ЦОД",
  "Small commercial backup and self-consumption": "Небольшой коммерческий резерв и автопотребление",
  "Solar and hybrid inverters": "Солнечные и гибридные инверторы",
  "Solar inverter variants": "Варианты солнечных инверторов",
  "Solution": "Решение",
  "Solution Detail": "Детали решения",
  "Solution Overview": "Обзор решения",
  "Solutions": "Решения",
  "Solutions Built Around Real Applications": "Решения, построенные вокруг реальных применений",
  "Solutions | Powerlink Energy": "Решения | Powerlink Energy",
  "Storage projects often need an easier way to explain battery, inverter, and accessory scope before detailed project engineering begins.": "Проектам накопления часто нужен более простой способ объяснить объём АКБ, инверторов и аксессуаров до начала детального проектирования.",
  "Submitting this form opens your default email client with a prefilled inquiry. If no mail client is available, contact us directly by email or WhatsApp.": "Отправка формы откроет ваш почтовый клиент с предзаполненным запросом. Если почтовый клиент недоступен, свяжитесь с нами по email или WhatsApp.",
  "Support": "Поддержка",
  "Supports bundled sourcing for field deployment.": "Поддерживает комплектную закупку для полевого развёртывания.",
  "Supports clearer project communication for monitoring applications.": "Способствует более ясной проектной коммуникации для приложений мониторинга.",
  "Supports distributed deployment across multiple station types.": "Поддерживает распределённое развёртывание на разных типах станций.",
  "Supports distributed power continuity for edge nodes.": "Обеспечивает распределённую непрерывность питания для edge-узлов.",
  "Supports integrated backup and storage discussions.": "Поддерживает обсуждения интегрированного резерва и накопления.",
  "Supports phased scaling for growing server loads.": "Поддерживает поэтапное масштабирование при росте серверных нагрузок.",
  "Supports practical category selection before system engineering.": "Поддерживает практичный выбор категорий до системного проектирования.",
  "Supports practical storage deployment discussions early in the sales cycle.": "Поддерживает практичные обсуждения развёртывания накопления на раннем этапе продаж.",
  "Supports residential backup and self-consumption discussions.": "Поддерживает обсуждения жилого резерва и автопотребления.",
  "Supports stable backup continuity.": "Обеспечивает стабильную непрерывность резерва.",
  "Supports telecom-focused projects with practical category scope.": "Поддерживает телеком-ориентированные проекты с практичным объёмом категорий.",
  "Talk to Our Team": "Поговорите с нашей командой",
  "Talk to Powerlink Energy": "Связаться с Powerlink Energy",
  "Talk to Us About Your Application": "Расскажите нам о вашем применении",
  "Telecom & DC Power": "Телеком и DC питание",
  "Telecom Base Station Backup Power": "Резервное питание телеком базовой станции",
  "Telecom Sites": "Телеком-объекты",
  "Telecom and DC power equipment": "Телеком и DC силовое оборудование",
  "Telecom and UPS power equipment": "Телеком и UPS силовое оборудование",
  "Telecom and distributed communications": "Телеком и распределённая связь",
  "Telecom backup power": "Телеком резервное питание",
  "Telecom backup power equipment reference": "Эталон телеком оборудования резервного питания",
  "Telecom power equipment and DC support modules for distributed communication sites and industrial power applications.": "Телеком-питание и DC модули поддержки для распределённых коммуникационных объектов и промышленных силовых приложений.",
  "Telecom power systems": "Телеком системы питания",
  "Telecom rectifier or UPS main power unit.": "Телеком выпрямитель или основной блок UPS питания.",
  "Telecom rectifier or backup host": "Телеком выпрямитель или резервный хост",
  "Telecom towers and distributed sites": "Телеком-вышки и распределённые объекты",
  "Tell us the scenario and target market so we can match the right solution path.": "Расскажите о сценарии и целевом рынке, чтобы мы подобрали правильный путь решения.",
  "Tell us what you need, and we will help you match the right solution for your application.": "Расскажите, что вам нужно — мы поможем подобрать подходящее решение для вашего применения.",
  "Tell us your application, power requirement, and target market. We will help you match the right solution quickly.": "Расскажите о применении, требованиях к мощности и целевом рынке. Мы быстро поможем подобрать подходящее решение.",
  "Tell us your application, target market, and expected quantity. We will help you match the right solution quickly.": "Расскажите о применении, целевом рынке и ожидаемом количестве. Мы быстро поможем подобрать подходящее решение.",
  "The framework combines an online UPS host, matched battery capacity, and practical distribution and monitoring accessories into one clear reference path.": "Фреймворк объединяет online UPS хост, согласованную ёмкость АКБ и практичные аксессуары распределения и мониторинга в один понятный эталонный путь.",
  "The framework combines storage units, inverter direction, and site integration accessories into one reusable project explanation model.": "Фреймворк объединяет блоки накопления, направление инвертора и аксессуары интеграции на объекте в одну многоразовую модель объяснения проекта.",
  "The reference structure combines telecom power equipment, storage, and key accessories in a format that is easier to discuss with buyers and project partners.": "Эталонная структура объединяет телеком-питание, накопление и ключевые аксессуары в формате, удобном для обсуждения с покупателями и проектными партнёрами.",
  "These visuals support early project discussions and will be replaced by verified customer project media when available.": "Эти визуалы поддерживают ранние проектные обсуждения и будут заменены проверенными материалами клиентских проектов, когда они станут доступны.",
  "This category covers telecom power equipment and DC support modules for distributed sites and related project environments.": "Эта категория охватывает телеком-питание и DC модули поддержки для распределённых объектов и связанных проектных сред.",
  "This category helps complete projects that need sensing accessories, monitoring items, and industrial cabling rather than only primary equipment.": "Эта категория помогает завершить проекты, которым нужны сенсорные аксессуары, компоненты мониторинга и промышленная кабельная система, а не только основное оборудование.",
  "This category supports solar and hybrid projects that require conversion equipment matched to storage or grid-linked application goals.": "Эта категория поддерживает солнечные и гибридные проекты, требующие преобразовательного оборудования, согласованного с целями накопления или подключения к сети.",
  "This framework explains a site-level storage package for commercial and industrial projects where backup support and energy optimization are both important.": "Этот фреймворк объясняет пакет накопления на уровне объекта для коммерческих и промышленных проектов, где важны и резерв, и оптимизация энергии.",
  "This framework explains a typical backup architecture for compact server rooms and IDC deployments that need clear runtime and continuity planning.": "Этот фреймворк объясняет типовую резервную архитектуру для компактных серверных и развёртываний IDC, требующих чёткого планирования автономной работы и непрерывности.",
  "This framework shows a common backup structure for telecom power projects that need resilient field deployment and practical maintenance logic.": "Этот фреймворк показывает типовую резервную структуру для телеком-проектов по питанию, требующих устойчивого полевого развёртывания и практичной логики обслуживания.",
  "This package is designed for home and light commercial users who need solar-linked storage, backup capability, and simple deployment logic.": "Этот пакет предназначен для домашних и лёгких коммерческих пользователей, которым нужно солнечное накопление, резервные возможности и простая логика развёртывания.",
  "This package supports distributed telecom sites that need dependable backup power, compact footprints, and straightforward maintenance.": "Этот пакет поддерживает распределённые телеком-объекты, которым нужно надёжное резервное питание, компактные габариты и простое обслуживание.",
  "This scenario serves distributed IT environments where compact backup power and reliable operation are needed close to the load.": "Этот сценарий обслуживает распределённые IT-среды, где рядом с нагрузкой нужны компактное резервное питание и надёжная работа.",
  "This section presents reusable application structures and reference content that can grow into a verified project library later.": "Этот раздел представляет многоразовые структуры применения и эталонный контент, который позже может вырасти в проверенную проектную библиотеку.",
  "This solution focuses on monitoring accessories and supporting power elements for safety supervision, sensing, and environmental alert scenarios.": "Это решение фокусируется на аксессуарах мониторинга и вспомогательных элементах питания для надзора за безопасностью, датчиков и сценариев экологических оповещений.",
  "This solution focuses on reliable backup power continuity for server rooms, network cabinets, and compact data center deployments where uptime matters.": "Это решение фокусируется на надёжной непрерывности резервного питания для серверных, сетевых шкафов и компактных развёртываний ЦОД, где важна бесперебойность.",
  "This solution targets site-level storage use cases such as peak shaving, time-of-use optimization, and backup support for commercial and industrial facilities.": "Это решение ориентировано на сценарии накопления на уровне объекта, такие как сглаживание пиков, оптимизация по времени использования и резервная поддержка для коммерческих и промышленных объектов.",
  "To help us respond faster, please include your application scenario, power range, target market, estimated quantity, and product category of interest.": "Чтобы мы ответили быстрее, укажите сценарий применения, диапазон мощности, целевой рынок, ожидаемое количество и интересующую категорию продукции.",
  "Toggle navigation": "Переключить навигацию",
  "Typical Equipment Scope for This Framework": "Типовой объём оборудования для этого фреймворка",
  "Typical Need": "Типовая потребность",
  "UPS Systems": "UPS системы",
  "UPS backup power equipment": "UPS оборудование резервного питания",
  "UPS host reference equipment": "Эталонное оборудование UPS хоста",
  "UPS runtime expansion": "Расширение автономной работы UPS",
  "UPS systems": "UPS системы",
  "UPS systems remain a core category for customers who need stable backup continuity across IT, telecom, and industrial use cases.": "UPS системы остаются ключевой категорией для клиентов, которым нужна стабильная непрерывность резерва в IT, телеком и промышленных сценариях.",
  "Understand": "Понять",
  "Use structured framework content to explain applications clearly now and add verified project photos later without changing the page system.": "Используйте структурированный контент фреймворка, чтобы ясно объяснить применения сейчас и позже добавить проверенные фото проектов без изменения системы страниц.",
  "Users want simpler product combinations instead of fragmented category selection.": "Пользователи хотят более простые комбинации продукции вместо фрагментированного выбора категорий.",
  "Verified Project Assets": "Проверенные проектные материалы",
  "Verified project media will be added after approval.": "Проверенные проектные материалы будут добавлены после одобрения.",
  "View details": "Подробнее",
  "We align storage direction with application goals, installation conditions, and expected delivery scope.": "Мы согласуем направление накопления с целями применения, условиями установки и ожидаемым объёмом поставки.",
  "We believe good supply support is not only about product availability. It is also about faster response, clearer communication, practical matching, and dependable follow-up.": "Мы считаем, что хорошая поддержка поставок — это не только доступность продукции. Это также более быстрый отклик, более ясная коммуникация, практичный подбор и надёжное сопровождение.",
  "We combine UPS, battery systems, DC/DC modules, inverters, and accessories into one practical sourcing path.": "Мы объединяем UPS, аккумуляторные системы, DC/DC модули, инверторы и аксессуары в один практичный канал закупки.",
  "We focus on combining practical products into workable power solutions for customers in data centers, telecom infrastructure, energy storage, edge computing, and other power-sensitive environments.": "Мы фокусируемся на объединении практичной продукции в работоспособные силовые решения для клиентов в центрах обработки данных, телеком-инфраструктуре, накоплении энергии, edge computing и других средах, чувствительных к питанию.",
  "We focus on how power hosts, batteries, conversion equipment, cabling, and monitoring accessories work together in real projects.": "Мы фокусируемся на том, как силовые хосты, АКБ, преобразовательное оборудование, кабельная система и аксессуары мониторинга работают вместе в реальных проектах.",
  "We focus on quick communication and practical configuration support based on the application, power requirement, and target market.": "Мы фокусируемся на быстрой коммуникации и практичной поддержке конфигурации на основе применения, требований к мощности и целевого рынка.",
  "We help clarify runtime targets, power range, installation constraints, and delivery scope before quotation.": "Мы помогаем уточнить цели автономной работы, диапазон мощности, ограничения установки и объём поставки до коммерческого предложения.",
  "We help combine power hosts, batteries, DC/DC modules, industrial cabling, and monitoring accessories into complete solution packages.": "Мы помогаем объединять силовые хосты, АКБ, DC/DC модули, промышленную кабельную систему и аксессуары мониторинга в полные пакеты решений.",
  "We help define the application environment, accessory scope, and integration priorities before quotation.": "Мы помогаем определить среду применения, объём аксессуаров и приоритеты интеграции до коммерческого предложения.",
  "We help evaluate footprint, runtime, and environment constraints before final category matching.": "Мы помогаем оценить габариты, автономную работу и ограничения среды до финального подбора категорий.",
  "We help match inverter and storage direction based on backup need, daily usage, and installation scenario.": "Мы помогаем согласовать направление инвертора и накопления на основе потребности в резерве, ежедневного использования и сценария установки.",
  "We help match product scope around station type, load profile, runtime target, and market requirement.": "Мы помогаем определить объём продукции с учётом типа станции, профиля нагрузки, цели автономной работы и требований рынка.",
  "We keep the discussion practical around requirement range, product scope, and quantity.": "Мы ведём практичное обсуждение вокруг диапазона требований, объёма продукции и количества.",
  "We keep the process simple: understand the application, match the configuration, and support communication through quotation and delivery coordination.": "Мы сохраняем процесс простым: понять применение, подобрать конфигурацию и поддерживать коммуникацию через коммерческое предложение и координацию поставки.",
  "We match products around applications such as data centers, telecom sites, storage projects, and edge environments.": "Мы подбираем продукцию для таких применений, как центры обработки данных, телеком-объекты, проекты накопления и edge-среды.",
  "We prioritize clear communication, quick matching, and timely follow-up during quotation and project discussion.": "Мы приоритезируем чёткую коммуникацию, быстрый подбор и своевременное сопровождение на этапах коммерческого предложения и обсуждения проекта.",
  "We prioritize timely feedback for customers who are evaluating or preparing a project inquiry.": "Мы приоритезируем своевременную обратную связь для клиентов, которые оценивают или готовят проектный запрос.",
  "We support both small-batch orders and longer-term project cooperation for customers who need practical supply support.": "Мы поддерживаем как малые партии, так и долгосрочное проектное сотрудничество для клиентов, которым нужна практичная поддержка поставок.",
  "We support customers in power-sensitive and mission-critical environments with practical, scenario-based solutions.": "Мы поддерживаем клиентов в средах, чувствительных к питанию и критически важных, практичными решениями на основе сценариев.",
  "We support early matching around site objectives, power range, and the practical boundary of supply scope.": "Мы поддерживаем ранний подбор с учётом целей объекта, диапазона мощности и практических границ объёма поставки.",
  "We support early-stage clarification around power range, backup duration, cabinet constraints, and sourcing scope.": "Мы поддерживаем уточнение на раннем этапе по диапазону мощности, длительности резерва, ограничениям шкафа и объёму закупки.",
  "We support practical order quantities for small-batch supply, pilot projects, and phased purchasing.": "Мы поддерживаем практичные объёмы заказа для малых партий, пилотных проектов и поэтапных закупок.",
  "We support practical scope definition around site conditions, autonomy targets, and delivery matching.": "Мы поддерживаем практичное определение объёма с учётом условий объекта, целей автономности и согласования поставки.",
  "We value efficient communication and practical support throughout product selection, quotation, and project follow-up.": "Мы ценим эффективную коммуникацию и практичную поддержку на всех этапах выбора продукции, коммерческого предложения и сопровождения проекта.",
  "Website": "Веб-сайт",
  "Website:": "Веб-сайт:",
  "What We Do": "Чем мы занимаемся",
  "WhatsApp": "WhatsApp",
  "WhatsApp Us": "Напишите нам в WhatsApp",
  "Why Buyers Choose This Category": "Почему покупатели выбирают эту категорию",
  "Why Choose Us": "Почему выбирают нас",
  "Why Powerlink Energy": "Почему Powerlink Energy",
  "Works well as part of integrated project packages.": "Хорошо работает как часть интегрированных проектных пакетов.",
  "Works with phased and scalable configurations.": "Работает с поэтапными и масштабируемыми конфигурациями.",
  "data center, telecom, storage, edge, monitoring": "центр обработки данных, телеком, накопление, edge, мониторинг",
  "direct, responsive, and solution-oriented": "прямой, оперативный и ориентированный на решения",
  "flexible for both project and phased purchasing": "гибкий для проектов и поэтапных закупок",
  "integrated supply path": "интегрированный канал поставки",
  "product categories": "категории продукции",
  "reference frameworks": "эталонные фреймворки",
  "solution scenarios": "сценарии решений"
}
